resolver/__init__.py
resolver/__main__.py
resolver/archive.py
resolver/mindeps/__init__.py
resolver/mindeps/__main__.py
python_resolver-0.0.2.post1.dist-info/LICENSE
python_resolver-0.0.2.post1.dist-info/METADATA
python_resolver-0.0.2.post1.dist-info/WHEEL
python_resolver-0.0.2.post1.dist-info/entry_points.txt
python_resolver-0.0.2.post1.dist-info/top_level.txt
python_resolver-0.0.2.post1.dist-info/RECORD
