Metadata-Version: 2.1
Name: python-resolver
Version: 0.0.2.post1
Summary: Python dependency resolver
Home-page: UNKNOWN
Author: Filipe Laíns
Author-email: lains@riseup.net
License: MIT
Project-URL: homepage, https://github.com/FFY00/python-resolver
Platform: UNKNOWN
Classifier: License :: OSI Approved :: MIT License
Classifier: Programming Language :: Python :: 3
Classifier: Programming Language :: Python :: 3 :: Only
Classifier: Programming Language :: Python :: 3.7
Classifier: Programming Language :: Python :: 3.8
Classifier: Programming Language :: Python :: 3.9
Requires-Python: >=3.7
License-File: LICENSE
Requires-Dist: importlib-metadata (>=3.2.0)
Requires-Dist: mousebender (~=2.0.0)
Requires-Dist: resolvelib (~=0.7.0)
Provides-Extra: mindeps
Requires-Dist: build (~=0.4.0) ; extra == 'mindeps'
Requires-Dist: pep517 ; extra == 'mindeps'
Provides-Extra: test
Requires-Dist: pytest (>=4) ; extra == 'test'
Requires-Dist: pytest-cov (>=2) ; extra == 'test'
